{
	"credit": "Made with Blockbench",
	"parent": "block/block",
	"textures": {
		"particle": "waystones:block/landing_stone",
		"texture": "waystones:block/landing_stone"
	},
	"elements": [
		{
			"name": "bordersouth",
			"from": [3, 0, 3],
			"to": [13, 1, 13],
			"rotation": {"angle": 0, "axis": "y", "origin": [8, 0, 8]},
			"faces": {
				"north": {"uv": [0, 0, 10, 1], "texture": "#texture"},
				"east": {"uv": [0, 9, 10, 10], "texture": "#texture"},
				"south": {"uv": [0, 9, 10, 10], "texture": "#texture"},
				"west": {"uv": [0, 0, 10, 1], "texture": "#texture"},
				"up": {"uv": [0, 0, 10, 10], "texture": "#texture"},
				"down": {"uv": [0, 0, 10, 10], "texture": "#texture"}
			}
		}
	]
}